{
"data": [
  { "name": "Admiral Piett (JTL)", "meta": 3.2, "win": 71, "matches": 7, "winCount": 5, "lossCount": 2, "drawCount": 0 },
  { "name": "Boba Fett (JTL)", "meta": 9.7, "win": 44, "matches": 16, "winCount": 7, "lossCount": 7, "drawCount": 2 },
  { "name": "Cad Bane (SHD)", "meta": 12.9, "win": 45, "matches": 20, "winCount": 9, "lossCount": 10, "drawCount": 1 },
  { "name": "Darth Vader (JTL)", "meta": 3.2, "win": 40, "matches": 5, "winCount": 2, "lossCount": 3, "drawCount": 0 },
  { "name": "Emperor Palpatine (SOR)", "meta": 9.7, "win": 29, "matches": 14, "winCount": 4, "lossCount": 6, "drawCount": 4 },
  { "name": "Gar Saxon (SHD)", "meta": 3.2, "win": 0, "matches": 4, "winCount": 0, "lossCount": 3, "drawCount": 1 },
  { "name": "Han Solo (SHD)", "meta": 3.2, "win": 50, "matches": 4, "winCount": 2, "lossCount": 2, "drawCount": 0 },
  { "name": "Han Solo (SOR)", "meta": 12.9, "win": 43, "matches": 23, "winCount": 10, "lossCount": 8, "drawCount": 5 },
  { "name": "Kylo Ren (LOF)", "meta": 3.2, "win": 57, "matches": 7, "winCount": 4, "lossCount": 2, "drawCount": 1 },
  { "name": "Kylo Ren (SHD)", "meta": 3.2, "win": 40, "matches": 5, "winCount": 2, "lossCount": 3, "drawCount": 0 },
  { "name": "Mother Talzin (LOF)", "meta": 3.2, "win": 40, "matches": 5, "winCount": 2, "lossCount": 2, "drawCount": 1 },
  { "name": "Obi-Wan Kenobi (LOF)", "meta": 3.2, "win": 40, "matches": 5, "winCount": 2, "lossCount": 3, "drawCount": 0 },
  { "name": "Obi-Wan Kenobi (TWI)", "meta": 3.2, "win": 50, "matches": 6, "winCount": 3, "lossCount": 2, "drawCount": 1 },
  { "name": "Qi&#x27;ra (SHD)", "meta": 6.5, "win": 60, "matches": 10, "winCount": 6, "lossCount": 4, "drawCount": 0 },
  { "name": "Rey (SHD)", "meta": 3.2, "win": 40, "matches": 5, "winCount": 2, "lossCount": 2, "drawCount": 1 },
  { "name": "Sabine Wren (SOR)", "meta": 9.7, "win": 50, "matches": 16, "winCount": 8, "lossCount": 7, "drawCount": 1 },
  { "name": "Third Sister (LOF)", "meta": 3.2, "win": 20, "matches": 5, "winCount": 1, "lossCount": 4, "drawCount": 0 },
  { "name": "Yoda (TWI)", "meta": 3.2, "win": 60, "matches": 5, "winCount": 3, "lossCount": 2, "drawCount": 0 }
]
}
