{
"data": [
  { "name": "Admiral Piett (JTL)", "meta": 8.7, "win": 80, "matches": 5 },
  { "name": "Anakin Skywalker (TWI)", "meta": 4.3, "win": 0, "matches": 4 },
  { "name": "Bo-Katan Kryze (SHD)", "meta": 4.3, "win": 40, "matches": 5 },
  { "name": "Cad Bane (SHD)", "meta": 4.3, "win": 100, "matches": 4 },
  { "name": "Emperor Palpatine (SOR)", "meta": 4.3, "win": 67, "matches": 3 },
  { "name": "Han Solo (SOR)", "meta": 13, "win": 0, "matches": 4 },
  { "name": "Iden Versio (SOR)", "meta": 4.3, "win": 33, "matches": 3 },
  { "name": "Kazuda Xiono (JTL)", "meta": 4.3, "win": 100, "matches": 1 },
  { "name": "Kylo Ren (SHD)", "meta": 4.3, "win": 25, "matches": 4 },
  { "name": "Luke Skywalker (JTL)", "meta": 8.7, "win": 80, "matches": 5 },
  { "name": "Mace Windu (TWI)", "meta": 4.3, "win": 0, "matches": 1 },
  { "name": "Qi&#x27;ra (SHD)", "meta": 8.7, "win": 50, "matches": 4 },
  { "name": "Quinlan Vos (TWI)", "meta": 4.3, "win": 0, "matches": 1 },
  { "name": "Rey (SHD)", "meta": 4.3, "win": 40, "matches": 5 },
  { "name": "Sabine Wren (SOR)", "meta": 13, "win": 67, "matches": 9 },
  { "name": "Yoda (TWI)", "meta": 4.3, "win": 0, "matches": 0 }
]
}
