{
"data": [
  { "name": "Admiral Piett (JTL)", "meta": 1.6, "win": 50, "matches": 6, "winCount": 3, "lossCount": 3, "drawCount": 0 },
  { "name": "Anakin Skywalker (LOF)", "meta": 1.6, "win": 0, "matches": 4, "winCount": 0, "lossCount": 4, "drawCount": 0 },
  { "name": "Anakin Skywalker (TWI)", "meta": 6.5, "win": 40, "matches": 20, "winCount": 8, "lossCount": 12, "drawCount": 0 },
  { "name": "Avar Kriss (LOF)", "meta": 3.2, "win": 50, "matches": 12, "winCount": 6, "lossCount": 6, "drawCount": 0 },
  { "name": "Boba Fett (JTL)", "meta": 9.7, "win": 56, "matches": 32, "winCount": 18, "lossCount": 10, "drawCount": 4 },
  { "name": "Bossk (SHD)", "meta": 1.6, "win": 0, "matches": 2, "winCount": 0, "lossCount": 2, "drawCount": 0 },
  { "name": "Cad Bane (SHD)", "meta": 6.5, "win": 75, "matches": 24, "winCount": 18, "lossCount": 6, "drawCount": 0 },
  { "name": "Cal Kestis (LOF)", "meta": 1.6, "win": 17, "matches": 6, "winCount": 1, "lossCount": 5, "drawCount": 0 },
  { "name": "Chancellor Palpatine (TWI)", "meta": 1.6, "win": 0, "matches": 5, "winCount": 0, "lossCount": 4, "drawCount": 1 },
  { "name": "Darth Maul (LOF)", "meta": 1.6, "win": 50, "matches": 6, "winCount": 3, "lossCount": 3, "drawCount": 0 },
  { "name": "Darth Vader (JTL)", "meta": 8.1, "win": 48, "matches": 29, "winCount": 14, "lossCount": 13, "drawCount": 2 },
  { "name": "Gar Saxon (SHD)", "meta": 4.8, "win": 27, "matches": 15, "winCount": 4, "lossCount": 11, "drawCount": 0 },
  { "name": "Grand Admiral Thrawn (JTL)", "meta": 1.6, "win": 25, "matches": 4, "winCount": 1, "lossCount": 3, "drawCount": 0 },
  { "name": "Grand Inquisitor (SOR)", "meta": 1.6, "win": 20, "matches": 5, "winCount": 1, "lossCount": 4, "drawCount": 0 },
  { "name": "Han Solo (SHD)", "meta": 11.3, "win": 45, "matches": 38, "winCount": 17, "lossCount": 19, "drawCount": 2 },
  { "name": "Han Solo (SOR)", "meta": 1.6, "win": 67, "matches": 6, "winCount": 4, "lossCount": 2, "drawCount": 0 },
  { "name": "Kazuda Xiono (JTL)", "meta": 1.6, "win": 33, "matches": 6, "winCount": 2, "lossCount": 4, "drawCount": 0 },
  { "name": "Kylo Ren (LOF)", "meta": 1.6, "win": 67, "matches": 6, "winCount": 4, "lossCount": 1, "drawCount": 1 },
  { "name": "Major Vonreg (JTL)", "meta": 1.6, "win": 25, "matches": 4, "winCount": 1, "lossCount": 3, "drawCount": 0 },
  { "name": "Mother Talzin (LOF)", "meta": 3.2, "win": 30, "matches": 10, "winCount": 3, "lossCount": 7, "drawCount": 0 },
  { "name": "Poe Dameron (JTL)", "meta": 1.6, "win": 50, "matches": 6, "winCount": 3, "lossCount": 3, "drawCount": 0 },
  { "name": "Quinlan Vos (TWI)", "meta": 9.7, "win": 58, "matches": 36, "winCount": 21, "lossCount": 12, "drawCount": 3 },
  { "name": "Rey (SHD)", "meta": 3.2, "win": 67, "matches": 12, "winCount": 8, "lossCount": 3, "drawCount": 1 },
  { "name": "Rio Durant (JTL)", "meta": 1.6, "win": 60, "matches": 5, "winCount": 3, "lossCount": 2, "drawCount": 0 },
  { "name": "Sabine Wren (SOR)", "meta": 8.1, "win": 41, "matches": 29, "winCount": 12, "lossCount": 17, "drawCount": 0 },
  { "name": "Yoda (TWI)", "meta": 3.2, "win": 64, "matches": 11, "winCount": 7, "lossCount": 4, "drawCount": 0 }
]
}
