{
"data": [
  { "name": "Admiral Ackbar (JTL)", "meta": 2.4, "win": 54, "matches": 13, "winCount": 7, "lossCount": 4, "drawCount": 2 },
  { "name": "Admiral Piett (JTL)", "meta": 3.6, "win": 47, "matches": 17, "winCount": 8, "lossCount": 8, "drawCount": 1 },
  { "name": "Admiral Trench (JTL)", "meta": 1.2, "win": 57, "matches": 7, "winCount": 4, "lossCount": 2, "drawCount": 1 },
  { "name": "Ahsoka Tano (TWI)", "meta": 1.2, "win": 57, "matches": 7, "winCount": 4, "lossCount": 3, "drawCount": 0 },
  { "name": "Anakin Skywalker (TWI)", "meta": 1.2, "win": 14, "matches": 7, "winCount": 1, "lossCount": 5, "drawCount": 1 },
  { "name": "Boba Fett (JTL)", "meta": 4.8, "win": 50, "matches": 28, "winCount": 14, "lossCount": 14, "drawCount": 0 },
  { "name": "Cad Bane (SHD)", "meta": 8.4, "win": 41, "matches": 49, "winCount": 20, "lossCount": 29, "drawCount": 0 },
  { "name": "Cal Kestis (LOF)", "meta": 1.2, "win": 43, "matches": 7, "winCount": 3, "lossCount": 4, "drawCount": 0 },
  { "name": "Captain Rex (TWI)", "meta": 1.2, "win": 71, "matches": 7, "winCount": 5, "lossCount": 2, "drawCount": 0 },
  { "name": "Darth Revan (LOF)", "meta": 1.2, "win": 0, "matches": 6, "winCount": 0, "lossCount": 6, "drawCount": 0 },
  { "name": "Darth Vader (JTL)", "meta": 4.8, "win": 33, "matches": 24, "winCount": 8, "lossCount": 16, "drawCount": 0 },
  { "name": "Darth Vader (SOR)", "meta": 2.4, "win": 38, "matches": 13, "winCount": 5, "lossCount": 8, "drawCount": 0 },
  { "name": "Emperor Palpatine (SOR)", "meta": 1.2, "win": 71, "matches": 7, "winCount": 5, "lossCount": 2, "drawCount": 0 },
  { "name": "Gar Saxon (SHD)", "meta": 7.2, "win": 48, "matches": 42, "winCount": 20, "lossCount": 22, "drawCount": 0 },
  { "name": "Grand Admiral Thrawn (JTL)", "meta": 3.6, "win": 62, "matches": 21, "winCount": 13, "lossCount": 7, "drawCount": 1 },
  { "name": "Han Solo (SHD)", "meta": 10.8, "win": 52, "matches": 58, "winCount": 30, "lossCount": 27, "drawCount": 1 },
  { "name": "Han Solo (SOR)", "meta": 8.4, "win": 59, "matches": 49, "winCount": 29, "lossCount": 19, "drawCount": 1 },
  { "name": "Iden Versio (SOR)", "meta": 2.4, "win": 76, "matches": 17, "winCount": 13, "lossCount": 4, "drawCount": 0 },
  { "name": "Kanan Jarrus (LOF)", "meta": 1.2, "win": 33, "matches": 6, "winCount": 2, "lossCount": 4, "drawCount": 0 },
  { "name": "Kazuda Xiono (JTL)", "meta": 3.6, "win": 55, "matches": 22, "winCount": 12, "lossCount": 8, "drawCount": 2 },
  { "name": "Kit Fisto (LOF)", "meta": 1.2, "win": 0, "matches": 3, "winCount": 0, "lossCount": 3, "drawCount": 0 },
  { "name": "Kylo Ren (LOF)", "meta": 1.2, "win": 25, "matches": 4, "winCount": 1, "lossCount": 3, "drawCount": 0 },
  { "name": "Luke Skywalker (JTL)", "meta": 3.6, "win": 48, "matches": 21, "winCount": 10, "lossCount": 11, "drawCount": 0 },
  { "name": "Obi-Wan Kenobi (LOF)", "meta": 3.6, "win": 24, "matches": 17, "winCount": 4, "lossCount": 13, "drawCount": 0 },
  { "name": "Poe Dameron (JTL)", "meta": 1.2, "win": 57, "matches": 7, "winCount": 4, "lossCount": 3, "drawCount": 0 },
  { "name": "Qi&#x27;ra (SHD)", "meta": 3.6, "win": 52, "matches": 21, "winCount": 11, "lossCount": 8, "drawCount": 2 },
  { "name": "Sabine Wren (SOR)", "meta": 7.2, "win": 46, "matches": 41, "winCount": 19, "lossCount": 19, "drawCount": 3 },
  { "name": "Third Sister (LOF)", "meta": 1.2, "win": 57, "matches": 7, "winCount": 4, "lossCount": 3, "drawCount": 0 },
  { "name": "Yoda (TWI)", "meta": 4.8, "win": 42, "matches": 24, "winCount": 10, "lossCount": 9, "drawCount": 5 }
]
}
