{
  "data": [
    { "value": 1, "name": "Droid Manufactory" },
    { "value": 1, "name": "Petranaki Arena" },
    { "value": 1, "name": "Pau City" },
    { "value": 1, "name": "Nabat Village" },
    { "value": 2, "name": "Lake Country" },
    { "value": 2, "name": "Thermal Oscillator" },
    { "value": 9, "name": "Red" },
    { "value": 17, "name": "Colossus" },
    { "value": 22, "name": "Green" },
    { "value": 42, "name": "Blue" },
    { "value": 52, "name": "Tarkintown" },
    { "value": 55, "name": "Yellow" },
    { "value": 59, "name": "ECL" },
    { "value": 144, "name": "Data Vault" }
  ]
}
