{
  "data": [
    { "value": 1, "name": "Kazuda Xiono (JTL) - Tarkintown" },
    { "value": 1, "name": "Cad Bane (SHD) - Blue" },
    { "value": 1, "name": "Emperor Palpatine (SOR) - Colossus" },
    { "value": 1, "name": "Admiral Ackbar (JTL) - Data Vault" },
    { "value": 1, "name": "Admiral Piett (JTL) - Red" },
    { "value": 1, "name": "Grand Admiral Thrawn (JTL) - Yellow" },
    { "value": 1, "name": "Han Solo (SHD) - Data Vault" },
    { "value": 1, "name": "Sabine Wren (SOR) - Nabat Village" },
    { "value": 1, "name": "Han Solo (JTL) - Tarkintown" },
    { "value": 1, "name": "Sabine Wren (SOR) - Tarkintown" },
    { "value": 1, "name": "Boba Fett (JTL) - Green" },
    { "value": 1, "name": "Han Solo (SHD) - Green Force" },
    { "value": 1, "name": "Darth Vader (JTL) - Yellow" },
    { "value": 1, "name": "Poe Dameron (JTL) - Data Vault" },
    { "value": 1, "name": "Han Solo (SHD) - Blue" },
    { "value": 2, "name": "Qi'ra (SHD) - Data Vault" },
    { "value": 2, "name": "Mother Talzin (LOF) - Red Force" },
    { "value": 2, "name": "Gar Saxon (SHD) - ECL" },
    { "value": 2, "name": "Iden Versio (SOR) - Data Vault" },
    { "value": 3, "name": "Emperor Palpatine (SOR) - Yellow" },
    { "value": 4, "name": "Yoda (TWI) - Red Force" },
    { "value": 5, "name": "Sabine Wren (SOR) - ECL" },
    { "value": 6, "name": "Kylo Ren (LOF) - Tarkintown" },
    { "value": 7, "name": "Anakin Skywalker (TWI) - Blue Force" },
    { "value": 8, "name": "Cad Bane (SHD) - Tarkintown" },
    { "value": 8, "name": "Boba Fett (JTL) - Data Vault" },
    { "value": 11, "name": "Quinlan Vos (TWI) - Tarkintown" },
    { "value": 13, "name": "Han Solo (SHD) - Blue Force" }
  ]
}
